addlicense/__init__.py
addlicense/addlicense.py
addlicense-0.0.2.dist-info/METADATA
addlicense-0.0.2.dist-info/RECORD
addlicense-0.0.2.dist-info/WHEEL
addlicense-0.0.2.dist-info/entry_points.txt
addlicense-0.0.2.dist-info/top_level.txt
