Metadata-Version: 2.1
Name: addlicense
Version: 0.0.2
Summary: addlicense automatically inserts a specified license file or copyright message at the top of one or more source code files
Home-page: https://github.com/hossg/addlicense
Author: Hossein Ghodse
Author-email: hossein.ghodse@gmail.com
License: UNKNOWN
Platform: UNKNOWN
Classifier: Programming Language :: Python :: 3
Classifier: License :: OSI Approved :: GNU Affero General Public License v3
Classifier: Operating System :: OS Independent
